{"1": ["yaleB01_P00A-070E+45.pgm", "yaleB01_P00A-110E+65.pgm", "yaleB01_P00A+060E+20.pgm", "yaleB01_P00A+035E+15.pgm", "yaleB01_P00A+005E-10.pgm", "yaleB01_P00A-035E-20.pgm", "yaleB01_P00A+000E+45.pgm", "yaleB01_P00A+035E-20.pgm", "yaleB01_P00A-070E+00.pgm", "yaleB01_P00A+000E+00.pgm", "yaleB01_P00A-095E+00.pgm", "yaleB01_P00A-130E+20.pgm", "yaleB01_P00A+035E+40.pgm", "yaleB01_P00A+000E+20.pgm", "yaleB01_P00A-010E-20.pgm"], "2": ["yaleB02_P00A+025E+00.pgm", "yaleB02_P00A+110E+15.pgm", "yaleB02_P00A-060E+20.pgm", "yaleB02_P00A-060E-20.pgm", "yaleB02_P00A-050E-40.pgm", "yaleB02_P00A+035E+15.pgm", "yaleB02_P00A+070E+00.pgm", "yaleB02_P00A+095E+00.pgm", "yaleB02_P00A+000E+20.pgm", "yaleB02_P00A-035E+65.pgm", "yaleB02_P00A-010E-20.pgm", "yaleB02_P00A-110E-20.pgm", "yaleB02_P00A-020E-40.pgm", "yaleB02_P00A-110E+65.pgm", "yaleB02_P00A-005E+10.pgm"], "3": ["yaleB03_P00A+000E+45.pgm", "yaleB03_P00A+085E+20.pgm", "yaleB03_P00A-110E+15.pgm", "yaleB03_P00A+110E+15.pgm", "yaleB03_P00A-130E+20.pgm", "yaleB03_P00A+000E+90.pgm", "yaleB03_P00A+110E+65.pgm", "yaleB03_P00A-010E-20.pgm", "yaleB03_P00A+095E+00.pgm", "yaleB03_P00A+000E-35.pgm", "yaleB03_P00A-005E-10.pgm", "yaleB03_P00A-035E+65.pgm", "yaleB03_P00A+050E+00.pgm", "yaleB03_P00A-070E-35.pgm", "yaleB03_P00A+110E+40.pgm"], "4": ["yaleB04_P00A+015E+20.pgm", "yaleB04_P00A+085E+20.pgm", "yaleB04_P00A-095E+00.pgm", "yaleB04_P00A+110E+40.pgm", "yaleB04_P00A+010E+00.pgm", "yaleB04_P00A+035E+65.pgm", "yaleB04_P00A+050E-40.pgm", "yaleB04_P00A-035E-20.pgm", "yaleB04_P00A-060E-20.pgm", "yaleB04_P00A-010E-20.pgm", "yaleB04_P00A+020E-10.pgm", "yaleB04_P00A+035E+15.pgm", "yaleB04_P00A+000E+45.pgm", "yaleB04_P00A-035E+40.pgm", "yaleB04_P00A+000E-20.pgm"], "5": ["yaleB05_P00A-095E+00.pgm", "yaleB05_P00A-025E+00.pgm", "yaleB05_P00A-110E-20.pgm", "yaleB05_P00A+070E+00.pgm", "yaleB05_P00A+085E-20.pgm", "yaleB05_P00A+000E+00.pgm", "yaleB05_P00A+070E+45.pgm", "yaleB05_P00A+005E+10.pgm", "yaleB05_P00A+010E-20.pgm", "yaleB05_P00A-070E+45.pgm", "yaleB05_P00A-010E-20.pgm", "yaleB05_P00A-035E-20.pgm", "yaleB05_P00A+010E+00.pgm", "yaleB05_P00A+000E+20.pgm", "yaleB05_P00A-005E-10.pgm"], "6": ["yaleB06_P00A+110E-20.pgm", "yaleB06_P00A+070E+00.pgm", "yaleB06_P00A-005E+10.pgm", "yaleB06_P00A+035E+40.pgm", "yaleB06_P00A+110E+65.pgm", "yaleB06_P00A+025E+00.pgm", "yaleB06_P00A+000E+90.pgm", "yaleB06_P00A+070E+45.pgm", "yaleB06_P00A-070E+00.pgm", "yaleB06_P00A+000E-35.pgm", "yaleB06_P00A+050E-40.pgm", "yaleB06_P00A+110E+15.pgm", "yaleB06_P00A+035E-20.pgm", "yaleB06_P00A-070E-35.pgm", "yaleB06_P00A-035E+15.pgm"], "7": ["yaleB07_P00A-015E+20.pgm", "yaleB07_P00A-020E-40.pgm", "yaleB07_P00A+000E+90.pgm", "yaleB07_P00A+095E+00.pgm", "yaleB07_P00A+085E+20.pgm", "yaleB07_P00A+070E-35.pgm", "yaleB07_P00A-110E+65.pgm", "yaleB07_P00A-070E+00.pgm", "yaleB07_P00A+015E+20.pgm", "yaleB07_P00A+110E+40.pgm", "yaleB07_P00_Ambient.pgm", "yaleB07_P00A-005E+10.pgm", "yaleB07_P00A-010E-20.pgm", "yaleB07_P00A+110E+15.pgm", "yaleB07_P00A-110E+40.pgm"], "8": ["yaleB08_P00A+010E+00.pgm", "yaleB08_P00A-060E+20.pgm", "yaleB08_P00A-070E+00.pgm", "yaleB08_P00A+060E+20.pgm", "yaleB08_P00A+000E-35.pgm", "yaleB08_P00A+095E+00.pgm", "yaleB08_P00A-110E+40.pgm", "yaleB08_P00A+005E+10.pgm", "yaleB08_P00A-020E-10.pgm", "yaleB08_P00A-010E+00.pgm", "yaleB08_P00A+060E-20.pgm", "yaleB08_P00A+035E+65.pgm", "yaleB08_P00A+000E+90.pgm", "yaleB08_P00A-085E+20.pgm", "yaleB08_P00A+010E-20.pgm"], "9": ["yaleB09_P00A+050E+00.pgm", "yaleB09_P00A+035E-20.pgm", "yaleB09_P00A+110E+40.pgm", "yaleB09_P00A-085E-20.pgm", "yaleB09_P00A+000E-20.pgm", "yaleB09_P00A+020E-10.pgm", "yaleB09_P00A-070E+00.pgm", "yaleB09_P00A-120E+00.pgm", "yaleB09_P00A+085E-20.pgm", "yaleB09_P00A+050E-40.pgm", "yaleB09_P00A+015E+20.pgm", "yaleB09_P00A+070E+45.pgm", "yaleB09_P00A+020E+10.pgm", "yaleB09_P00_Ambient.pgm", "yaleB09_P00A+025E+00.pgm"], "10": ["yaleB10_P00A+005E-10.pgm", "yaleB10_P00A-070E-35.pgm", "yaleB10_P00A-085E-20.pgm", "yaleB10_P00A+120E+00.pgm", "yaleB10_P00A+020E+10.pgm", "yaleB10_P00A-095E+00.pgm", "yaleB10_P00A+015E+20.pgm", "yaleB10_P00A+035E+40.pgm", "yaleB10_P00A-120E+00.pgm", "yaleB10_P00A-085E+20.pgm", "yaleB10_P00A+020E-10.pgm", "yaleB10_P00A+020E-40.pgm", "yaleB10_P00A-060E-20.pgm", "yaleB10_P00A-110E+65.pgm", "yaleB10_P00A+085E+20.pgm"], "11": ["yaleB11_P00A-010E+00.pgm", "yaleB11_P00A-070E-35.pgm", "yaleB11_P00A+005E+10.pgm", "yaleB11_P00A+035E+40.pgm", "yaleB11_P00A-085E-20.pgm", "yaleB11_P00A+015E+20.pgm", "yaleB11_P00A-110E-20.pgm", "yaleB11_P00A-010E-20.pgm", "yaleB11_P00A+025E+00.pgm", "yaleB11_P00A+110E+65.pgm", "yaleB11_P00A-005E+10.pgm", "yaleB11_P00A+020E-40.pgm", "yaleB11_P00A-070E+45.pgm", "yaleB11_P00A+000E+45.pgm", "yaleB11_P00A-070E+00.pgm"], "12": ["yaleB12_P00A-060E+20.pgm", "yaleB12_P00A-110E+40.pgm", "yaleB12_P00A+005E-10.pgm", "yaleB12_P00A+020E+10.pgm", "yaleB12_P00A-010E-20.pgm", "yaleB12_P00_Ambient.pgm", "yaleB12_P00A+000E+00.pgm", "yaleB12_P00A-020E+10.pgm", "yaleB12_P00A-025E+00.pgm", "yaleB12_P00A-035E-20.pgm", "yaleB12_P00A-035E+65.pgm", "yaleB12_P00A-020E-40.pgm", "yaleB12_P00A-005E-10.pgm", "yaleB12_P00A+110E+40.pgm", "yaleB12_P00A-070E+00.pgm"], "13": ["yaleB13_P00A+015E+20.pgm", "yaleB13_P00A-035E+15.pgm", "yaleB13_P00A-095E+00.pgm", "yaleB13_P00A+060E-20.pgm", "yaleB13_P00A+070E-35.pgm", "yaleB13_P00A+130E+20.pgm", "yaleB13_P00A-005E-10.pgm", "yaleB13_P00A-085E-20.pgm", "yaleB13_P00A-070E+00.pgm", "yaleB13_P00A+005E+10.pgm", "yaleB13_P00A+000E-20.pgm", "yaleB13_P00A-110E+40.pgm", "yaleB13_P00A+035E+40.pgm", "yaleB13_P00A+000E+90.pgm", "yaleB13_P00A+110E+65.pgm"], "15": ["yaleB15_P00A+035E+15.pgm", "yaleB15_P00A-010E-20.pgm", "yaleB15_P00A+060E-20.pgm", "yaleB15_P00A-085E-20.pgm", "yaleB15_P00A-120E+00.pgm", "yaleB15_P00A-005E-10.pgm", "yaleB15_P00A-020E-10.pgm", "yaleB15_P00A-035E+15.pgm", "yaleB15_P00A+035E+65.pgm", "yaleB15_P00A+000E+90.pgm", "yaleB15_P00A+035E+40.pgm", "yaleB15_P00A+050E-40.pgm", "yaleB15_P00A+120E+00.pgm", "yaleB15_P00A+000E+00.pgm", "yaleB15_P00A-110E+40.pgm"], "16": ["yaleB16_P00A+000E-35.pgm", "yaleB16_P00A+050E+00.pgm", "yaleB16_P00A+110E-20.pgm", "yaleB16_P00A+035E+15.pgm", "yaleB16_P00A-035E+15.pgm", "yaleB16_P00A+050E-40.pgm", "yaleB16_P00A+005E-10.pgm", "yaleB16_P00A+010E+00.pgm", "yaleB16_P00A-070E+00.pgm", "yaleB16_P00A+025E+00.pgm", "yaleB16_P00A+060E+20.pgm", "yaleB16_P00A-085E+20.pgm", "yaleB16_P00A+110E+40.pgm", "yaleB16_P00A+005E+10.pgm", "yaleB16_P00A+110E+15.pgm"], "17": ["yaleB17_P00A-070E+45.pgm", "yaleB17_P00A-020E+10.pgm", "yaleB17_P00A+015E+20.pgm", "yaleB17_P00A+050E+00.pgm", "yaleB17_P00A+060E+20.pgm", "yaleB17_P00A+095E+00.pgm", "yaleB17_P00A-130E+20.pgm", "yaleB17_P00A+035E-20.pgm", "yaleB17_P00A+020E+10.pgm", "yaleB17_P00A+120E+00.pgm", "yaleB17_P00A+070E+45.pgm", "yaleB17_P00A+000E-20.pgm", "yaleB17_P00A+035E+15.pgm", "yaleB17_P00A-110E+15.pgm", "yaleB17_P00A+010E-20.pgm"], "18": ["yaleB18_P00A+110E+65.pgm", "yaleB18_P00A-060E+20.pgm", "yaleB18_P00A+050E+00.pgm", "yaleB18_P00A-005E+10.pgm", "yaleB18_P00A+050E-40.pgm", "yaleB18_P00A+085E+20.pgm", "yaleB18_P00A-035E+15.pgm", "yaleB18_P00A+005E+10.pgm", "yaleB18_P00A-020E+10.pgm", "yaleB18_P00A+110E+40.pgm", "yaleB18_P00A-020E-10.pgm", "yaleB18_P00A+095E+00.pgm", "yaleB18_P00A+035E+40.pgm", "yaleB18_P00A-120E+00.pgm", "yaleB18_P00A-130E+20.pgm"], "19": ["yaleB19_P00A+035E+65.pgm", "yaleB19_P00A-010E-20.pgm", "yaleB19_P00A+085E+20.pgm", "yaleB19_P00A+110E+15.pgm", "yaleB19_P00A-095E+00.pgm", "yaleB19_P00A+005E+10.pgm", "yaleB19_P00A+000E+45.pgm", "yaleB19_P00A+070E+00.pgm", "yaleB19_P00A+130E+20.pgm", "yaleB19_P00A+110E+65.pgm", "yaleB19_P00A+070E-35.pgm", "yaleB19_P00A+025E+00.pgm", "yaleB19_P00A+000E+00.pgm", "yaleB19_P00A+015E+20.pgm", "yaleB19_P00A-110E+40.pgm"], "20": ["yaleB20_P00A-060E+20.pgm", "yaleB20_P00A+060E+20.pgm", "yaleB20_P00A+020E+10.pgm", "yaleB20_P00A+000E-20.pgm", "yaleB20_P00A-070E+45.pgm", "yaleB20_P00A-060E-20.pgm", "yaleB20_P00A+035E-20.pgm", "yaleB20_P00A+000E-35.pgm", "yaleB20_P00A+050E-40.pgm", "yaleB20_P00A+000E+90.pgm", "yaleB20_P00A-025E+00.pgm", "yaleB20_P00A+070E+45.pgm", "yaleB20_P00A-130E+20.pgm", "yaleB20_P00A+085E-20.pgm", "yaleB20_P00A-110E+40.pgm"], "21": ["yaleB21_P00A-110E+65.pgm", "yaleB21_P00A-060E-20.pgm", "yaleB21_P00A-095E+00.pgm", "yaleB21_P00A+010E-20.pgm", "yaleB21_P00A-085E-20.pgm", "yaleB21_P00A+020E-10.pgm", "yaleB21_P00A-130E+20.pgm", "yaleB21_P00_Ambient.pgm", "yaleB21_P00A-025E+00.pgm", "yaleB21_P00A+095E+00.pgm", "yaleB21_P00A-035E+65.pgm", "yaleB21_P00A-110E+40.pgm", "yaleB21_P00A+110E+40.pgm", "yaleB21_P00A-120E+00.pgm", "yaleB21_P00A-085E+20.pgm"], "22": ["yaleB22_P00A-120E+00.pgm", "yaleB22_P00A-050E+00.pgm", "yaleB22_P00A+120E+00.pgm", "yaleB22_P00A-095E+00.pgm", "yaleB22_P00A+020E+10.pgm", "yaleB22_P00A+035E+15.pgm", "yaleB22_P00A-005E-10.pgm", "yaleB22_P00A+000E-35.pgm", "yaleB22_P00A+005E-10.pgm", "yaleB22_P00A+050E+00.pgm", "yaleB22_P00A-110E+15.pgm", "yaleB22_P00A+095E+00.pgm", "yaleB22_P00A-015E+20.pgm", "yaleB22_P00A-010E+00.pgm", "yaleB22_P00A-050E-40.pgm"], "23": ["yaleB23_P00A+010E-20.pgm", "yaleB23_P00A-035E+40.pgm", "yaleB23_P00A+110E+15.pgm", "yaleB23_P00A+005E+10.pgm", "yaleB23_P00A-020E-10.pgm", "yaleB23_P00A+060E+20.pgm", "yaleB23_P00A-010E+00.pgm", "yaleB23_P00A+000E+20.pgm", "yaleB23_P00A-005E+10.pgm", "yaleB23_P00A+020E+10.pgm", "yaleB23_P00A+020E-10.pgm", "yaleB23_P00A-070E-35.pgm", "yaleB23_P00A-095E+00.pgm", "yaleB23_P00A+005E-10.pgm", "yaleB23_P00A+035E+65.pgm"], "24": ["yaleB24_P00A+005E-10.pgm", "yaleB24_P00A+130E+20.pgm", "yaleB24_P00A-020E+10.pgm", "yaleB24_P00A+035E-20.pgm", "yaleB24_P00A+015E+20.pgm", "yaleB24_P00A+060E-20.pgm", "yaleB24_P00A-005E+10.pgm", "yaleB24_P00A+000E+45.pgm", "yaleB24_P00A-095E+00.pgm", "yaleB24_P00A-070E+00.pgm", "yaleB24_P00A-050E-40.pgm", "yaleB24_P00A+025E+00.pgm", "yaleB24_P00A+050E-40.pgm", "yaleB24_P00A-110E+40.pgm", "yaleB24_P00A+010E-20.pgm"], "25": ["yaleB25_P00A+095E+00.pgm", "yaleB25_P00A+085E+20.pgm", "yaleB25_P00_Ambient.pgm", "yaleB25_P00A-005E+10.pgm", "yaleB25_P00A-035E+65.pgm", "yaleB25_P00A+070E+00.pgm", "yaleB25_P00A+110E+15.pgm", "yaleB25_P00A-050E-40.pgm", "yaleB25_P00A-070E+00.pgm", "yaleB25_P00A+005E+10.pgm", "yaleB25_P00A+020E-40.pgm", "yaleB25_P00A+005E-10.pgm", "yaleB25_P00A+035E+65.pgm", "yaleB25_P00A-110E+15.pgm", "yaleB25_P00A-035E-20.pgm"], "26": ["yaleB26_P00A-095E+00.pgm", "yaleB26_P00A+025E+00.pgm", "yaleB26_P00A-010E-20.pgm", "yaleB26_P00A+095E+00.pgm", "yaleB26_P00A+020E-10.pgm", "yaleB26_P00A-005E+10.pgm", "yaleB26_P00A+035E-20.pgm", "yaleB26_P00A-110E+40.pgm", "yaleB26_P00A-085E-20.pgm", "yaleB26_P00A+110E+40.pgm", "yaleB26_P00A-060E+20.pgm", "yaleB26_P00A-120E+00.pgm", "yaleB26_P00A+060E-20.pgm", "yaleB26_P00A-035E+40.pgm", "yaleB26_P00A-025E+00.pgm"], "27": ["yaleB27_P00A+110E+15.pgm", "yaleB27_P00A-025E+00.pgm", "yaleB27_P00A-005E+10.pgm", "yaleB27_P00A-110E+40.pgm", "yaleB27_P00A+010E-20.pgm", "yaleB27_P00A-035E+15.pgm", "yaleB27_P00A+110E+65.pgm", "yaleB27_P00A-050E-40.pgm", "yaleB27_P00A+000E-35.pgm", "yaleB27_P00A-015E+20.pgm", "yaleB27_P00A+000E+45.pgm", "yaleB27_P00A+000E-20.pgm", "yaleB27_P00A-060E+20.pgm", "yaleB27_P00A+085E+20.pgm", "yaleB27_P00A+060E+20.pgm"], "28": ["yaleB28_P00A-035E+15.pgm", "yaleB28_P00A-020E-10.pgm", "yaleB28_P00A+110E+40.pgm", "yaleB28_P00A-110E+65.pgm", "yaleB28_P00A-120E+00.pgm", "yaleB28_P00A+095E+00.pgm", "yaleB28_P00A+000E-35.pgm", "yaleB28_P00A-085E+20.pgm", "yaleB28_P00A-070E+45.pgm", "yaleB28_P00A+110E-20.pgm", "yaleB28_P00A+085E+20.pgm", "yaleB28_P00A-035E+40.pgm", "yaleB28_P00A-050E+00.pgm", "yaleB28_P00A-050E-40.pgm", "yaleB28_P00A+060E+20.pgm"], "29": ["yaleB29_P00A+000E-20.pgm", "yaleB29_P00A+110E+40.pgm", "yaleB29_P00A-060E-20.pgm", "yaleB29_P00A+095E+00.pgm", "yaleB29_P00A-110E+15.pgm", "yaleB29_P00A+110E+15.pgm", "yaleB29_P00A+000E+90.pgm", "yaleB29_P00A+020E+10.pgm", "yaleB29_P00A+015E+20.pgm", "yaleB29_P00A+020E-10.pgm", "yaleB29_P00A-020E+10.pgm", "yaleB29_P00A+005E+10.pgm", "yaleB29_P00A+000E+20.pgm", "yaleB29_P00A-070E-35.pgm", "yaleB29_P00A+035E-20.pgm"], "30": ["yaleB30_P00A+005E-10.pgm", "yaleB30_P00A-095E+00.pgm", "yaleB30_P00A+020E-10.pgm", "yaleB30_P00A+010E-20.pgm", "yaleB30_P00A+035E+40.pgm", "yaleB30_P00A-085E+20.pgm", "yaleB30_P00A-035E+65.pgm", "yaleB30_P00A+095E+00.pgm", "yaleB30_P00_Ambient.pgm", "yaleB30_P00A+000E-20.pgm", "yaleB30_P00A-120E+00.pgm", "yaleB30_P00A-025E+00.pgm", "yaleB30_P00A-110E+15.pgm", "yaleB30_P00A+025E+00.pgm", "yaleB30_P00A+085E-20.pgm"], "31": ["yaleB31_P00A-050E+00.pgm", "yaleB31_P00A-025E+00.pgm", "yaleB31_P00A+025E+00.pgm", "yaleB31_P00A+000E+45.pgm", "yaleB31_P00A+005E-10.pgm", "yaleB31_P00A-095E+00.pgm", "yaleB31_P00A-060E+20.pgm", "yaleB31_P00A+095E+00.pgm", "yaleB31_P00A-015E+20.pgm", "yaleB31_P00A-035E-20.pgm", "yaleB31_P00A-130E+20.pgm", "yaleB31_P00A-070E+00.pgm", "yaleB31_P00A-110E+65.pgm", "yaleB31_P00A-110E+40.pgm", "yaleB31_P00A+010E-20.pgm"], "32": ["yaleB32_P00A+060E+20.pgm", "yaleB32_P00A+120E+00.pgm", "yaleB32_P00A+110E+40.pgm", "yaleB32_P00A-015E+20.pgm", "yaleB32_P00A+050E+00.pgm", "yaleB32_P00A+000E+90.pgm", "yaleB32_P00A+035E+65.pgm", "yaleB32_P00A+070E+45.pgm", "yaleB32_P00A+110E-20.pgm", "yaleB32_P00A+070E+00.pgm", "yaleB32_P00A+035E-20.pgm", "yaleB32_P00A-130E+20.pgm", "yaleB32_P00A+020E+10.pgm", "yaleB32_P00A+110E+65.pgm", "yaleB32_P00A-070E+00.pgm"], "33": ["yaleB33_P00A-035E-20.pgm", "yaleB33_P00A-005E-10.pgm", "yaleB33_P00A+000E+45.pgm", "yaleB33_P00A-110E+15.pgm", "yaleB33_P00A-020E-40.pgm", "yaleB33_P00A-110E+65.pgm", "yaleB33_P00A+025E+00.pgm", "yaleB33_P00A+020E-10.pgm", "yaleB33_P00A-085E+20.pgm", "yaleB33_P00A+130E+20.pgm", "yaleB33_P00A-085E-20.pgm", "yaleB33_P00A+085E+20.pgm", "yaleB33_P00A+060E-20.pgm", "yaleB33_P00A-050E-40.pgm", "yaleB33_P00A-060E+20.pgm"], "34": ["yaleB34_P00A-110E+40.pgm", "yaleB34_P00A+110E+40.pgm", "yaleB34_P00A-020E-10.pgm", "yaleB34_P00A-060E+20.pgm", "yaleB34_P00A+110E-20.pgm", "yaleB34_P00A+120E+00.pgm", "yaleB34_P00A+000E-20.pgm", "yaleB34_P00A+020E-10.pgm", "yaleB34_P00A-025E+00.pgm", "yaleB34_P00_Ambient.pgm", "yaleB34_P00A+060E-20.pgm", "yaleB34_P00A-070E+45.pgm", "yaleB34_P00A+085E+20.pgm", "yaleB34_P00A+000E+00.pgm", "yaleB34_P00A-070E-35.pgm"], "35": ["yaleB35_P00A-070E+00.pgm", "yaleB35_P00A-060E+20.pgm", "yaleB35_P00A+005E-10.pgm", "yaleB35_P00A+020E+10.pgm", "yaleB35_P00A-020E+10.pgm", "yaleB35_P00A+000E+20.pgm", "yaleB35_P00A+000E-20.pgm", "yaleB35_P00A+005E+10.pgm", "yaleB35_P00A+050E-40.pgm", "yaleB35_P00A+000E+45.pgm", "yaleB35_P00A+010E+00.pgm", "yaleB35_P00A-010E-20.pgm", "yaleB35_P00A+035E+65.pgm", "yaleB35_P00A+130E+20.pgm", "yaleB35_P00A-070E+45.pgm"], "36": ["yaleB36_P00A-060E+20.pgm", "yaleB36_P00A-120E+00.pgm", "yaleB36_P00A-005E-10.pgm", "yaleB36_P00_Ambient.pgm", "yaleB36_P00A-020E+10.pgm", "yaleB36_P00A+035E+40.pgm", "yaleB36_P00A-110E-20.pgm", "yaleB36_P00A+085E-20.pgm", "yaleB36_P00A+035E+15.pgm", "yaleB36_P00A-050E+00.pgm", "yaleB36_P00A-025E+00.pgm", "yaleB36_P00A+060E+20.pgm", "yaleB36_P00A-110E+15.pgm", "yaleB36_P00A+070E+45.pgm", "yaleB36_P00A-110E+40.pgm"], "37": ["yaleB37_P00A-010E+00.pgm", "yaleB37_P00A-060E-20.pgm", "yaleB37_P00A+035E+15.pgm", "yaleB37_P00_Ambient.pgm", "yaleB37_P00A+095E+00.pgm", "yaleB37_P00A-050E+00.pgm", "yaleB37_P00A+110E+15.pgm", "yaleB37_P00A+010E+00.pgm", "yaleB37_P00A+130E+20.pgm", "yaleB37_P00A+035E+40.pgm", "yaleB37_P00A+035E+65.pgm", "yaleB37_P00A-035E+40.pgm", "yaleB37_P00A+085E+20.pgm", "yaleB37_P00A+000E+45.pgm", "yaleB37_P00A+000E-35.pgm"], "38": ["yaleB38_P00A-050E-40.pgm", "yaleB38_P00A-070E+45.pgm", "yaleB38_P00A+005E-10.pgm", "yaleB38_P00A-010E+00.pgm", "yaleB38_P00A+035E+40.pgm", "yaleB38_P00A-110E+15.pgm", "yaleB38_P00A+000E+00.pgm", "yaleB38_P00A-110E+40.pgm", "yaleB38_P00A-085E-20.pgm", "yaleB38_P00_Ambient.pgm", "yaleB38_P00A+095E+00.pgm", "yaleB38_P00A+000E-20.pgm", "yaleB38_P00A+000E+45.pgm", "yaleB38_P00A-085E+20.pgm", "yaleB38_P00A-035E-20.pgm"], "39": ["yaleB39_P00A-060E-20.pgm", "yaleB39_P00A+000E+00.pgm", "yaleB39_P00A-005E-10.pgm", "yaleB39_P00A+000E+45.pgm", "yaleB39_P00A+060E+20.pgm", "yaleB39_P00A-110E-20.pgm", "yaleB39_P00A+070E+00.pgm", "yaleB39_P00A+070E-35.pgm", "yaleB39_P00A-035E+40.pgm", "yaleB39_P00A+020E-40.pgm", "yaleB39_P00A+050E+00.pgm", "yaleB39_P00A-110E+40.pgm", "yaleB39_P00A-035E+65.pgm", "yaleB39_P00A-130E+20.pgm", "yaleB39_P00A-005E+10.pgm"]}